MANIFEST.in
README.md
pyproject.toml
plotter_core/__init__.py
plotter_core/analyzer.py
plotter_core/loader.py
plotter_core/server.py
plotter_core.egg-info/PKG-INFO
plotter_core.egg-info/SOURCES.txt
plotter_core.egg-info/dependency_links.txt
plotter_core.egg-info/requires.txt
plotter_core.egg-info/top_level.txt
plotter_core/static/404.html
plotter_core/static/__next.__PAGE__.txt
plotter_core/static/__next._full.txt
plotter_core/static/__next._head.txt
plotter_core/static/__next._index.txt
plotter_core/static/__next._tree.txt
plotter_core/static/_not-found.html
plotter_core/static/_not-found.txt
plotter_core/static/favicon.ico
plotter_core/static/file.svg
plotter_core/static/globe.svg
plotter_core/static/index.html
plotter_core/static/index.txt
plotter_core/static/next.svg
plotter_core/static/vercel.svg
plotter_core/static/window.svg
plotter_core/static/_next/static/3n9gyrOdRvxmC5REhJkQG/_buildManifest.js
plotter_core/static/_next/static/3n9gyrOdRvxmC5REhJkQG/_clientMiddlewareManifest.json
plotter_core/static/_next/static/3n9gyrOdRvxmC5REhJkQG/_ssgManifest.js
plotter_core/static/_next/static/chunks/105ffb4b083bd562.js
plotter_core/static/_next/static/chunks/3cbd7a85d3273830.js
plotter_core/static/_next/static/chunks/4fd93823156e59e8.js
plotter_core/static/_next/static/chunks/6020b0f158eeb104.js
plotter_core/static/_next/static/chunks/67678304b4502f62.js
plotter_core/static/_next/static/chunks/a6dad97d9634a72d.js
plotter_core/static/_next/static/chunks/a6dad97d9634a72d.js.map
plotter_core/static/_next/static/chunks/cc759f7c2413b7ff.js
plotter_core/static/_next/static/chunks/f760c31673e92894.css
plotter_core/static/_next/static/chunks/fe85151b3556ac68.js
plotter_core/static/_next/static/chunks/turbopack-99d558f7ee7b0bc4.js
plotter_core/static/_next/static/media/4fa387ec64143e14-s.c1fdd6c2.woff2
plotter_core/static/_next/static/media/7178b3e590c64307-s.b97b3418.woff2
plotter_core/static/_next/static/media/797e433ab948586e-s.p.dbea232f.woff2
plotter_core/static/_next/static/media/8a480f0b521d4e75-s.8e0177b5.woff2
plotter_core/static/_next/static/media/bbc41e54d2fcbd21-s.799d8ef8.woff2
