Metadata-Version: 2.4
Name: plotter-core
Version: 0.1.1
Summary: A split-stack Data Analysis & Plotting library.
Author-email: TBA5854 <tba235854@gmail.com>
Requires-Python: >=3.9
Requires-Dist: fastapi
Requires-Dist: pandas
Requires-Dist: uvicorn
Requires-Dist: python-multipart
Requires-Dist: openpyxl
